README.rst
setup.py
multiprocessing_generator/__init__.py
multiprocessing_generator/tests.py
multiprocessing_generator.egg-info/PKG-INFO
multiprocessing_generator.egg-info/SOURCES.txt
multiprocessing_generator.egg-info/dependency_links.txt
multiprocessing_generator.egg-info/top_level.txt