Metadata-Version: 1.1
Name: multiprocessing-generator
Version: 0.1
Summary: Prefetch elements from a Python generator in the background, from a separate process
Home-page: https://github.com/wetneb/multiprocessing_generator
Author: Antonin Delpeuch
Author-email: firstname@lastname.eu
License: MIT
Keywords: multiprocessing generator prefetch
Platform: UNKNOWN
Classifier: Development Status :: 3 - Alpha
Classifier: Intended Audience :: Developers
Classifier: License :: OSI Approved :: MIT License
Classifier: Programming Language :: Python :: 2.7
